tx_elections_scrapers/__init__.py
tx_elections_scrapers/sos/__init__.py
tx_elections_scrapers/sos/fips.py
tx_elections_scrapers/sos/interpret_county.py
tx_elections_scrapers/sos/interpret_statewide.py
tx_elections_scrapers/sos/serialize_county.py
tx_elections_scrapers/sos/serialize_statewide.py
tx_elections_scrapers/sos/test_interpret_county.py
tx_elections_scrapers/sos/test_interpret_statewide.py
tx_elections_scrapers/sos/test_serialize_county.py
tx_elections_scrapers/sos/test_serialize_statewide.py
tx_elections_scrapers/sos/test_sos.py
tx_elections_scrapers/sos/test_utils.py
tx_elections_scrapers/sos/utils.py
tx_elections_scrapers-0.4.1.dist-info/DESCRIPTION.rst
tx_elections_scrapers-0.4.1.dist-info/entry_points.txt
tx_elections_scrapers-0.4.1.dist-info/METADATA
tx_elections_scrapers-0.4.1.dist-info/metadata.json
tx_elections_scrapers-0.4.1.dist-info/RECORD
tx_elections_scrapers-0.4.1.dist-info/top_level.txt
tx_elections_scrapers-0.4.1.dist-info/WHEEL
