Metadata-Version: 2.0
Name: tx-elections-scrapers
Version: 0.4.1
Summary: Scrapers for Texas elections results
Home-page: https://github.com/texastribune/tx_election_scrapers
Author: Chris Chang
Author-email: c@crccheck.com
License: Apache License, Version 2.0
Platform: UNKNOWN
Classifier: Development Status :: 2 - Pre-Alpha
Classifier: Intended Audience :: Developers
Classifier: License :: OSI Approved :: BSD License
Classifier: Programming Language :: Python :: 2
Classifier: Programming Language :: Python :: 2.7
Requires-Dist: PyYAML
Requires-Dist: docopt
Requires-Dist: lxml
Requires-Dist: python-dateutil
